mummify/__init__.py
mummify/cli.py
mummify/main.py
mummify-0.3.0.dist-info/DESCRIPTION.rst
mummify-0.3.0.dist-info/METADATA
mummify-0.3.0.dist-info/RECORD
mummify-0.3.0.dist-info/WHEEL
mummify-0.3.0.dist-info/entry_points.txt
mummify-0.3.0.dist-info/metadata.json
mummify-0.3.0.dist-info/top_level.txt
