Metadata-Version: 2.0
Name: mummify
Version: 0.3.0
Summary: Git + Logging for ML
Home-page: https://github.com/maxhumber/mummify
Author: Max Humber
Author-email: max.humber@gmail.com
License: MIT
Platform: UNKNOWN
Classifier: Development Status :: 3 - Alpha
Classifier: Intended Audience :: Developers
Classifier: License :: OSI Approved :: MIT License
Classifier: Natural Language :: English
Classifier: Operating System :: OS Independent
Classifier: Programming Language :: Python :: 3
Classifier: Programming Language :: Python :: 3.6
Classifier: Topic :: Software Development :: Version Control
Classifier: Topic :: Software Development :: Libraries :: Python Modules
Requires-Python: >=3.6
